dog/__init__.py
dog/averager.py
dog/dog.py
dog_optimizer-1.0.2.dist-info/LICENSE
dog_optimizer-1.0.2.dist-info/METADATA
dog_optimizer-1.0.2.dist-info/WHEEL
dog_optimizer-1.0.2.dist-info/top_level.txt
dog_optimizer-1.0.2.dist-info/RECORD
