Metadata-Version: 2.1
Name: dog-optimizer
Version: 1.0.2
Summary: implementation of the algorithms in the paper DoG is SGD's Best Friend: A Parameter-Free Dynamic Step Size Schedule
Author: Maor Ivgi, Oliver Hinder, Yair Carmon
Project-URL: Homepage, https://github.com/formll/dog
Project-URL: Paper, https://arxiv.org/abs/2302.12022
Classifier: Programming Language :: Python :: 3
Classifier: License :: OSI Approved :: MIT License
Classifier: Operating System :: OS Independent
Requires-Python: >=3.7
License-File: LICENSE
